ipreputation/__init__.py
ipreputation/client.py
ipreputation-0.0.1.dist-info/DESCRIPTION.rst
ipreputation-0.0.1.dist-info/METADATA
ipreputation-0.0.1.dist-info/RECORD
ipreputation-0.0.1.dist-info/WHEEL
ipreputation-0.0.1.dist-info/metadata.json
ipreputation-0.0.1.dist-info/top_level.txt
tests/__init__.py
tests/test_client.py
