Metadata-Version: 2.0
Name: ipreputation
Version: 0.0.1
Summary: IP Reputation Python Client
Home-page: https://github.com/mozilla-services/ip-reputation-python-client
Author: Mozilla Services
Author-email: services-dev@mozilla.com
License: MPL (2.0)
Keywords: web services
Platform: UNKNOWN
Classifier: Programming Language :: Python
Classifier: Programming Language :: Python :: 2
Classifier: Programming Language :: Python :: 2.7
Classifier: Programming Language :: Python :: 3
Classifier: Programming Language :: Python :: 3.5
Classifier: License :: OSI Approved :: Mozilla Public License 2.0 (MPL 2.0)
Requires-Dist: mohawk
Requires-Dist: requests
Requires-Dist: requests-hawk
Requires-Dist: six
